tle_download/__init__.py
tle_download/main.py
tle_download-0.1.0.dist-info/entry_points.txt
tle_download-0.1.0.dist-info/WHEEL
tle_download-0.1.0.dist-info/METADATA
tle_download-0.1.0.dist-info/LICENSE
tle_download-0.1.0.dist-info/RECORD
