Metadata-Version: 2.1
Name: tle-download
Version: 0.1.0
Summary: A small utility to download TLEs from Space Track.
License: MIT
Author-email: Cognitive Space <paul@cognitivespace.com>
Requires-Python: >=3.7
Classifier: License :: OSI Approved :: MIT License
Classifier: Programming Language :: Python :: 3
Classifier: Programming Language :: Python :: 3.10
Classifier: Programming Language :: Python :: 3.7
Classifier: Programming Language :: Python :: 3.8
Classifier: Programming Language :: Python :: 3.9
Requires-Dist: httpx~=0.20
Requires-Dist: typer~=0.4
Project-URL: homepage, https://github.com/cognitive-space/tle-download
